boonlab/__init__.py
boonlab/display.py
boonlab/hashes.py
boonlab/pandas.py
boonlab/plot.py
boonlab/proxies.py
boonlab-1.0.0.dist-info/LICENSE.txt
boonlab-1.0.0.dist-info/METADATA
boonlab-1.0.0.dist-info/WHEEL
boonlab-1.0.0.dist-info/top_level.txt
boonlab-1.0.0.dist-info/RECORD
